{
  "colorPalette": "electric-blue",
  "glassSurfaces": false,
  "glassmorphic": false,
  "entries": [
    {
      "id": "20260719-204622-rqhz",
      "title": "Sho Long I Tripped",
      "commanders": [
        "Sho Long I Tripped"
      ],
      "dateStart": "2026-07-20T00:46:22.000Z",
      "dateEnd": "2026-07-20T01:52:55.000Z",
      "dateLabel": "7/19/2026, 8:46:22 PM - 7/19/2026, 9:52:55 PM",
      "url": "https://Alexcionix.github.io/myst-wvw-logs/?report=20260719-204622-rqhz",
      "summary": {
        "borderlandsPct": 1,
        "mapSlices": [
          {
            "name": "Red Borderlands",
            "value": 17,
            "color": "#ef4444"
          },
          {
            "name": "Blue Borderlands",
            "value": 9,
            "color": "#3b82f6"
          }
        ],
        "avgSquadSize": 20,
        "avgEnemySize": 14
      }
    },
    {
      "id": "20260718-210047-erah",
      "title": "Durgadurg",
      "commanders": [
        "Durgadurg"
      ],
      "dateStart": "2026-07-19T01:00:47.000Z",
      "dateEnd": "2026-07-19T01:50:34.000Z",
      "dateLabel": "7/18/2026, 9:00:47 PM - 7/18/2026, 9:50:34 PM",
      "url": "https://Alexcionix.github.io/myst-wvw-logs/?report=20260718-210047-erah",
      "summary": {
        "borderlandsPct": 1,
        "mapSlices": [
          {
            "name": "Green Borderlands",
            "value": 25,
            "color": "#22c55e"
          },
          {
            "name": "Red Borderlands",
            "value": 6,
            "color": "#ef4444"
          }
        ],
        "avgSquadSize": 20,
        "avgEnemySize": 17
      }
    },
    {
      "id": "20260714-211354-sdwt",
      "title": "Clever Blackbird",
      "commanders": [
        "Clever Blackbird"
      ],
      "dateStart": "2026-07-15T01:13:54.000Z",
      "dateEnd": "2026-07-15T02:01:38.000Z",
      "dateLabel": "7/14/2026, 9:13:54 PM - 7/14/2026, 10:01:38 PM",
      "url": "https://Alexcionix.github.io/myst-wvw-logs/?report=20260714-211354-sdwt",
      "summary": {
        "borderlandsPct": 1,
        "mapSlices": [
          {
            "name": "Blue Borderlands",
            "value": 11,
            "color": "#3b82f6"
          },
          {
            "name": "Green Borderlands",
            "value": 1,
            "color": "#22c55e"
          }
        ],
        "avgSquadSize": 29,
        "avgEnemySize": 35
      }
    }
  ]
}